MANIFEST.in
README.rst
requirements.txt
setup.cfg
setup.py
lor/__init__.py
lor/__main__.py
lor/_constants.py
lor/_internal.py
lor/_paths.py
lor/cmdline.py
lor/generator.py
lor/path.py
lor/props.py
lor/test.py
lor/workspace.py
lor.egg-info/PKG-INFO
lor.egg-info/SOURCES.txt
lor.egg-info/dependency_links.txt
lor.egg-info/entry_points.txt
lor.egg-info/requires.txt
lor.egg-info/top_level.txt
lor/commands/__init__.py
lor/commands/dot.py
lor/commands/explain.py
lor/commands/generate.py
lor/commands/ls.py
lor/commands/new.py
lor/commands/properties.py
lor/commands/run.py
lor/generators/__init__.py
lor/generators/generator/__init__.py
lor/generators/generator/generator_generator.py
lor/generators/generator/templates/generator.py.jinja2
lor/generators/task/__init__.py
lor/generators/task/task_generator.py
lor/generators/task/templates/task.py.jinja2
lor/generators/task/templates/test_task.py.jinja2
lor/generators/workspace/__init__.py
lor/generators/workspace/workspace_generator.py
lor/generators/workspace/templates/README.rst.jinja2
lor/generators/workspace/templates/install
lor/generators/workspace/templates/lor
lor/generators/workspace/templates/pkg_init.py
lor/generators/workspace/templates/requirements.txt
lor/generators/workspace/templates/setup.py.jinja2
lor/tasks/__init__.py
lor/tasks/fs.py
lor/tasks/general.py
lor/tasks/hdfs.py
lor/tasks/tar.py
lor/util/__init__.py
lor/util/cli.py
lor/util/reflection.py
lor/util/subprocess.py