Metadata-Version: 1.2
Name: lor
Version: 0.0.13
Summary: A framework for rapidly developing pipelines with Luigi
Home-page: UNKNOWN
Author: Adam Kewley
Author-email: contact@adamkewley.com
License: Apache License 2.0
Keywords: Luigi
Platform: UNKNOWN
Classifier: Development Status :: 3 - Alpha
Classifier: Intended Audience :: Developers
Classifier: Programming Language :: Python :: 3
Requires-Python: >=3.4
